reddit_api/__init__.py
reddit_api/api.py
reddit_api/debug.py
reddit_api/decorator.py
reddit_api/etl.py
reddit_api/tools.py
reddit_api-0.4.dist-info/LICENSE
reddit_api-0.4.dist-info/METADATA
reddit_api-0.4.dist-info/WHEEL
reddit_api-0.4.dist-info/entry_points.txt
reddit_api-0.4.dist-info/top_level.txt
reddit_api-0.4.dist-info/RECORD
