Metadata-Version: 2.1
Name: reddit-api
Version: 0.4
Summary: Reddit API for Airflow
Author: Unknwon
License-File: LICENSE
Requires-Dist: praw
Requires-Dist: yake
Requires-Dist: pandas
Requires-Dist: pyarrow
Requires-Dist: colorlog
Provides-Extra: dev
Requires-Dist: pytest ; extra == 'dev'
Requires-Dist: pytest-cov ; extra == 'dev'
Requires-Dist: flake8 ; extra == 'dev'
Requires-Dist: black ; extra == 'dev'
Requires-Dist: isort ; extra == 'dev'
Requires-Dist: mypy ; extra == 'dev'
Requires-Dist: pylint ; extra == 'dev'
Requires-Dist: pre-commit ; extra == 'dev'
Requires-Dist: tox ; extra == 'dev'
Requires-Dist: twine ; extra == 'dev'
Requires-Dist: wheel ; extra == 'dev'
